upstash_workflow/__init__.py
upstash_workflow/asyncio/__init__.py
upstash_workflow/asyncio/context/__init__.py
upstash_workflow/asyncio/context/auto_executor.py
upstash_workflow/asyncio/context/context.py
upstash_workflow/asyncio/context/steps.py
upstash_workflow/asyncio/serve/__init__.py
upstash_workflow/asyncio/serve/authorization.py
upstash_workflow/asyncio/serve/options.py
upstash_workflow/asyncio/serve/serve.py
upstash_workflow/asyncio/workflow_parser.py
upstash_workflow/asyncio/workflow_requests.py
upstash_workflow/constants.py
upstash_workflow/context/__init__.py
upstash_workflow/context/auto_executor.py
upstash_workflow/context/context.py
upstash_workflow/context/steps.py
upstash_workflow/error.py
upstash_workflow/fastapi.py
upstash_workflow/flask.py
upstash_workflow/serve/__init__.py
upstash_workflow/serve/authorization.py
upstash_workflow/serve/options.py
upstash_workflow/serve/serve.py
upstash_workflow/types.py
upstash_workflow/utils.py
upstash_workflow/workflow_parser.py
upstash_workflow/workflow_requests.py
upstash_workflow/workflow_types.py
upstash_workflow-0.1.3.dist-info/LICENSE
upstash_workflow-0.1.3.dist-info/METADATA
upstash_workflow-0.1.3.dist-info/WHEEL
upstash_workflow-0.1.3.dist-info/RECORD
