Metadata-Version: 2.1
Name: upstash-workflow
Version: 0.1.3
Summary: Python SDK for Upstash Workflow
Home-page: https://github.com/upstash/workflow-py
License: MIT
Keywords: Workflow,Upstash Workflow,Durable Serverless Functions
Author: Upstash
Author-email: support@upstash.com
Maintainer: Upstash
Maintainer-email: support@upstash.com
Requires-Python: >=3.8,<4.0
Classifier: Development Status :: 5 - Production/Stable
Classifier: Intended Audience :: Developers
Classifier: License :: OSI Approved :: MIT License
Classifier: Operating System :: OS Independent
Classifier: Programming Language :: Python
Classifier: Programming Language :: Python :: 3
Classifier: Programming Language :: Python :: 3.8
Classifier: Programming Language :: Python :: 3.9
Classifier: Programming Language :: Python :: 3.10
Classifier: Programming Language :: Python :: 3.11
Classifier: Programming Language :: Python :: 3.12
Classifier: Programming Language :: Python :: 3.13
Classifier: Programming Language :: Python :: 3 :: Only
Classifier: Programming Language :: Python :: Implementation :: CPython
Classifier: Topic :: Software Development :: Libraries
Requires-Dist: qstash (>=2.0.3,<3.0.0)
Project-URL: Repository, https://github.com/upstash/workflow-py
